batchimage/__init__.py
batchimage/annotate.py
batchimage/batch_image_cli.py
batchimage/batch_image_module.py
batchimage/compress.py
batchimage/convert.py
batchimage/logger.py
batchimage/multiprocess.py
batchimage/process_files.py
batchimage/resize.py
batchimage/timestamp.py
batchimage/validate.py
batchimage-0.3.2.dist-info/entry_points.txt
batchimage-0.3.2.dist-info/WHEEL
batchimage-0.3.2.dist-info/METADATA
batchimage-0.3.2.dist-info/RECORD
