Metadata-Version: 2.1
Name: batchimage
Version: 0.3.2
Summary: Batch Image Converter
Home-page: https://pypi.org/project/batchimage/
Keywords: image,cli,batch image,converter,opencv,multithreaded,pictures,compress
Author: Sumanth
Author-email: sumanthreddystar@gmail.com
Maintainer: Sumanth
Maintainer-email: sumanthreddystar@gmail.com
Requires-Python: >=3.6,<4.0
Classifier: Programming Language :: Python :: 3
Classifier: Programming Language :: Python :: 3.10
Classifier: Programming Language :: Python :: 3.6
Classifier: Programming Language :: Python :: 3.7
Classifier: Programming Language :: Python :: 3.8
Classifier: Programming Language :: Python :: 3.9
Requires-Dist: opencv-python (>=4.5.0,<5.0.0)
Requires-Dist: typer (>=0.6.1,<0.7.0)
Project-URL: Bug Tracker, https://github.com/insumanth/batchimage/issues
Project-URL: Documentation, https://github.com/insumanth/batchimage/blob/main/README.md
Project-URL: Repository, https://github.com/insumanth/batchimage
